pyquickstart/cli.py
pyquickstart/config.py
pyquickstart/error.py
pyquickstart/project.py
pyquickstart/templates/standard/cookiecutter.json
pyquickstart/templates/standard/{{cookiecutter.project}}/.gitignore
pyquickstart/templates/standard/{{cookiecutter.project}}/.gitlab-ci.yml
pyquickstart/templates/standard/{{cookiecutter.project}}/CHANGELOG.md
pyquickstart/templates/standard/{{cookiecutter.project}}/LICENSE
pyquickstart/templates/standard/{{cookiecutter.project}}/MANIFEST.in
pyquickstart/templates/standard/{{cookiecutter.project}}/README.md
pyquickstart/templates/standard/{{cookiecutter.project}}/setup.cfg
pyquickstart/templates/standard/{{cookiecutter.project}}/setup.py
pyquickstart/templates/standard/{{cookiecutter.project}}/tox.ini
pyquickstart/templates/standard/{{cookiecutter.project}}/src/foundation/error.py
pyquickstart/templates/standard/{{cookiecutter.project}}/tests/__init__.py
pyquickstart/templates/standard/{{cookiecutter.project}}/tests/foundation/__init__.py
pyquickstart/templates/standard/{{cookiecutter.project}}/tests/foundation/test_error.py
pyquickstart-2.0.0.dist-info/LICENSE
pyquickstart-2.0.0.dist-info/METADATA
pyquickstart-2.0.0.dist-info/WHEEL
pyquickstart-2.0.0.dist-info/entry_points.txt
pyquickstart-2.0.0.dist-info/top_level.txt
pyquickstart-2.0.0.dist-info/RECORD
