Metadata-Version: 2.1
Name: pyquickstart
Version: 2.0.0
Summary: Create Python projects easily using well-defined templates.
Home-page: https://gitlab.com/texperience/pyquickstart
Author: Timo Rieber
Author-email: trieber@texperience.de
License: MIT License (MIT)
Platform: UNKNOWN
Classifier: Development Status :: 5 - Production/Stable
Classifier: Environment :: Console
Classifier: Intended Audience :: Developers
Classifier: License :: OSI Approved :: MIT License
Classifier: Operating System :: OS Independent
Classifier: Programming Language :: Python
Classifier: Programming Language :: Python :: 3
Classifier: Programming Language :: Python :: 3.7
Classifier: Programming Language :: Python :: 3.8
Classifier: Programming Language :: Python :: 3.9
Classifier: Programming Language :: Python :: 3.10
Classifier: Topic :: Software Development
License-File: LICENSE
Requires-Dist: click (<9.0,>=8.0)
Requires-Dist: cookiecutter (<2.0,>=1.7)
Provides-Extra: development
Requires-Dist: brunette (==0.2.0) ; extra == 'development'
Requires-Dist: coverage (<7.0,>=6.3) ; extra == 'development'
Requires-Dist: flake8 (<5.0,>=4.0) ; extra == 'development'
Requires-Dist: isort (<6.0,>=5.10) ; extra == 'development'
Requires-Dist: mypy (<1.0,>=0.931) ; extra == 'development'
Requires-Dist: pytest (<8.0,>=7.0) ; extra == 'development'
Requires-Dist: pytest-mock (<4.0,>=3.7) ; extra == 'development'
Requires-Dist: tox (<4.0,>=3.24) ; extra == 'development'
